{
    "storymap": {
        "call_to_action": true,
        "call_to_action_text": "",
        "map_as_image": false,
        "slides": [
            {
                "date": "",
                "text": {
                    "headline": "1902-11-29",
                    "text": ""
                },
                "location": {
                    "line": true
                },
                "type": "overview"
            },
            {
                "date": "",
                "text": {
                    "headline": "",
                    "text": " 曇、 "
                }
            },
            {
                "date": "",
                "text": {
                    "headline": "08:00:00",
                    "text": "<time when=\"08:00:00\"> 午前八時 </time>\n<persname corresp=\"#pers_小出粲\">\n<surname> 小出 </surname>\n<forename> 粲 </forename>\n</persname> 氏来ル、 "
                }
            },
            {
                "date": "",
                "text": {
                    "headline": "09:00:00",
                    "text": "<time when=\"09:00:00\"> 九時 </time> 過 <placename corresp=\"#place_日本橋兜町\"> 兜町\n       </placename> 事務所ニ抵リ来人ニ接ス、 "
                },
                "location": {
                    "line": true,
                    "lat": 35.6814833,
                    "lon": 139.7777861,
                    "zoom": 8
                }
            },
            {
                "date": "",
                "text": {
                    "headline": "10:30:00",
                    "text": "<time when=\"10:30:00\"> 十時半 </time>\n       宮中ニ参内シテ謁ヲ賜ハル、蓋シ欧米旅行ヨリ帰京セシニヨリ此事アリシモノナラン、 <persname corresp=\"#pers_井上\">\n<surname> 井上 </surname>\n</persname> 公使其他海軍武官モ共ニ此栄アリキ、 "
                }
            },
            {
                "date": "",
                "text": {
                    "headline": "11:00:00",
                    "text": "<time when=\"11:00:00\"> 十一時 </time>\n<placename corresp=\"#place_日本橋兜町\"> 兜町 </placename> ニ抵リ <orgname> 東京瓦斯会社 </orgname>\n       ノ事ニ関シ株主中ノ五氏ト協議ス、 <persname corresp=\"#pers_渡辺福三郎\">\n<surname> 渡辺 </surname>\n<forename> 福三郎 </forename>\n</persname> 氏同席ス、畢テ事務ヲ視テ "
                },
                "location": {
                    "line": true,
                    "lat": 35.6814833,
                    "lon": 139.7777861,
                    "zoom": 8
                }
            },
            {
                "date": "",
                "text": {
                    "headline": "17:00:00",
                    "text": "<time when=\"17:00:00\"> 午後五時 </time>\n<placename corresp=\"#place_上野\"> 上野 </placename>\n<orgname> 精養軒 </orgname> ニ抵リ、 <orgname> 高等商業学校 </orgname> 教員等ノ催フセル宴会ニ出席ス、食卓上一場ノ演説ヲ為シ、夜 "
                },
                "location": {
                    "line": true,
                    "lat": 35.7089139,
                    "lon": 139.7742361,
                    "zoom": 8
                }
            },
            {
                "date": "",
                "text": {
                    "headline": "21:00:00",
                    "text": "<time when=\"21:00:00\"> 九時 </time>\n<placename corresp=\"#place_飛鳥山邸\"> 王子別荘 </placename> ニ帰宿ス "
                }
            }
        ],
        "zoomify": false,
        "map_type": "osm:standard",
        "map_subdomains": "",
        "attribution": "",
        "language": "jp"
    },
    "font_css": "stock:opensans-gentiumbook"
}