{
    "storymap": {
        "call_to_action": true,
        "call_to_action_text": "",
        "map_as_image": false,
        "slides": [
            {
                "date": "",
                "text": {
                    "headline": "1908-10-05",
                    "text": ""
                },
                "location": {
                    "line": true
                },
                "type": "overview"
            },
            {
                "date": "",
                "text": {
                    "headline": "",
                    "text": "\n"
                }
            },
            {
                "date": "",
                "text": {
                    "headline": "08:00:00",
                    "text": "<time when=\"08:00:00\"> 午前八時 </time> 起床、直ニ朝飧ヲ食シ、一来客ニ接ス、 <persname corresp=\"#pers_神谷義雄\">\n<surname> 神谷 </surname>\n<forename> 義雄 </forename>\n</persname> 、 <persname corresp=\"#pers_山辺丈夫\">\n<surname> 山辺 </surname>\n<forename> 丈夫 </forename>\n</persname> 二氏来訪セシモ、外出ニ際スルニヨリテ謝絶ス、 "
                }
            },
            {
                "date": "",
                "text": {
                    "headline": "09:30:00",
                    "text": "<time when=\"09:30:00\"> 午前九時半 </time>\n<persname corresp=\"#pers_桂\">\n<surname> 桂 </surname>\n</persname> 総理大臣ヲ官舎ニ訪ヒ、鉄道公債ノ件ニ関シ談話ス、 <persname corresp=\"#pers_豊川\">\n<surname> 豊川 </surname>\n</persname> 、 <persname corresp=\"#pers_早川\">\n<surname> 早川 </surname>\n</persname> 、 <persname corresp=\"#pers_園田\">\n<surname> 園田 </surname>\n</persname> 、 <persname corresp=\"#pers_原\">\n<surname> 原 </surname>\n</persname> 四氏同席ス、畢テ <persname corresp=\"#pers_近藤廉平\">\n<surname> 近藤 </surname>\n<forename> 廉平 </forename>\n</persname> 氏ト共ニ <placename corresp=\"#place_東京\"> 東京 </placename>\n       鉄道ノ件ニ関シ種々内情ヲ陳述シテ、電車賃直上ノ已ムヲ得サルヲ説ク、 "
                }
            },
            {
                "date": "",
                "text": {
                    "headline": "12:00:00",
                    "text": "<time when=\"12:00:00\"> 十二時 </time>\n<orgname> 第一銀行 </orgname> ニ抵リテ午飧シ、 "
                }
            },
            {
                "date": "",
                "text": {
                    "headline": "13:00:00",
                    "text": "<time when=\"13:00:00\"> 午後一時 </time>\n       銀行集会所ニ抵リ、米艦隊歓迎会ノ事ヲ協議ス、畢テ <placename corresp=\"#place_日本橋兜町\"> 兜町 </placename> 事務所ニ抵リ、 <persname corresp=\"#pers_曾禰寛治\">\n<surname> 曾禰 </surname>\n<forename> 寛治 </forename>\n</persname> 其他ノ来人ニ接シ、又書状ヲ裁ス、 "
                },
                "location": {
                    "line": true,
                    "lat": 35.6814833,
                    "lon": 139.7777861,
                    "zoom": 8
                }
            },
            {
                "date": "",
                "text": {
                    "headline": "16:00:00",
                    "text": "<time when=\"16:00:00\"> 四時 </time> 過 <persname corresp=\"#pers_平田\">\n<surname> 平田 </surname>\n</persname> 内務大臣ヲ官舎ニ訪ヒ、 <placename corresp=\"#place_東京\"> 東京 </placename> 鉄道ノ事ヲ談ス、 "
                }
            },
            {
                "date": "",
                "text": {
                    "headline": "19:00:00",
                    "text": "<time when=\"19:00:00\"> 七時 </time>\n<placename corresp=\"#place_王子\"> 王子 </placename> ニ帰 <pb corresp=\"#pageB1541\" facs=\"https://eiichi.shibusawa.or.jp/denkishiryo-bekkan/api/images/iiif/567/full/max/0/default.jpg\" n=\"B1541\" source=\"#pageB1541\"></pb> 宿ス、夜、 <persname corresp=\"#pers_酒匂\">\n<surname> 酒匂 </surname>\n</persname> 氏ト電話ニテ要務ヲ談ス "
                }
            }
        ],
        "zoomify": false,
        "map_type": "osm:standard",
        "map_subdomains": "",
        "attribution": "",
        "language": "jp"
    },
    "font_css": "stock:opensans-gentiumbook"
}