{
    "storymap": {
        "call_to_action": true,
        "call_to_action_text": "",
        "map_as_image": false,
        "slides": [
            {
                "date": "",
                "text": {
                    "headline": "1908-07-21",
                    "text": ""
                },
                "location": {
                    "line": true
                },
                "type": "overview"
            },
            {
                "date": "",
                "text": {
                    "headline": "",
                    "text": "\n"
                }
            },
            {
                "date": "",
                "text": {
                    "headline": "06:00:00",
                    "text": "<time when=\"06:00:00\"> 午前六時 </time> 起床、入浴シ、畢テ朝飧ヲ食ス、 "
                }
            },
            {
                "date": "",
                "text": {
                    "headline": "08:30:00",
                    "text": "<time when=\"08:30:00\"> 午前八時半 </time>\n<placename corresp=\"#place_王子\"> 王子 </placename> 発ノ汽車ニ搭シテ <orgname> 日本煉瓦会社 </orgname>\n       ノ工場上敷面村《（免）》ニ抵ル、 "
                }
            },
            {
                "date": "",
                "text": {
                    "headline": "11:00:00",
                    "text": "<time when=\"11:00:00\"> 十一時 </time>\n       工場着、先ツ各工場ヲ一覧シ、後、株主総会ヲ開キ、畢テ午飧ヲ食ス、職員一同食卓ニ就ク、食事後一場ノ演説ヲ為ス、又、揮毫ヲ試ミ、 "
                }
            },
            {
                "date": "",
                "text": {
                    "headline": "16:00:00",
                    "text": "<time when=\"16:00:00\"> 午後四時\n       </time> 過ノ <placename corresp=\"#place_深谷\"> 深谷 </placename> 発汽車ニテ "
                }
            },
            {
                "date": "",
                "text": {
                    "headline": "19:00:00",
                    "text": "<time when=\"19:00:00\"> 七時 </time>\n<placename corresp=\"#place_王子\"> 王子 </placename> ニ帰宿ス、夜、雑誌類ヲ一覧ス "
                }
            }
        ],
        "zoomify": false,
        "map_type": "osm:standard",
        "map_subdomains": "",
        "attribution": "",
        "language": "jp"
    },
    "font_css": "stock:opensans-gentiumbook"
}