{
    "storymap": {
        "call_to_action": true,
        "call_to_action_text": "",
        "map_as_image": false,
        "slides": [
            {
                "date": "",
                "text": {
                    "headline": "1908-07-25",
                    "text": ""
                },
                "location": {
                    "line": true
                },
                "type": "overview"
            },
            {
                "date": "",
                "text": {
                    "headline": "",
                    "text": "\n"
                }
            },
            {
                "date": "",
                "text": {
                    "headline": "06:00:00",
                    "text": "<time when=\"06:00:00\"> 午前六時 </time> 起床、入浴シ、畢テ朝飧ヲ食ス、後、書状ヲ裁ス、 "
                }
            },
            {
                "date": "",
                "text": {
                    "headline": "11:00:00",
                    "text": "<time when=\"11:00:00\"> 午前十一時 </time>\n<orgname>\n<orgname> 帝国ホテル </orgname>\n</orgname> ニ抵リ午飧シ、後、株主総会ヲ開キ要件ヲ議決ス、午後 <placename corresp=\"#place_日本橋兜町\"> 兜町 </placename>\n       事務所ニ抵リ来人ニ接シ又事務ヲ処理ス、 "
                },
                "location": {
                    "line": true,
                    "lat": 35.6814833,
                    "lon": 139.7777861,
                    "zoom": 8
                }
            },
            {
                "date": "",
                "text": {
                    "headline": "14:00:00",
                    "text": "<time when=\"14:00:00\"> 午後二時 </time> 大日本製糖会社ノ重役会ニ <placename corresp=\"#place_日本橋\"> 日本橋 </placename> 倶楽部ニ出席ス、 <persname corresp=\"#pers_酒匂\">\n<surname> 酒匂 </surname>\n</persname> 氏身上ニ関スル過日来ノ事ヲ重役ニ談話ス、 <placename corresp=\"#place_浜町\"> 浜町 </placename> 宅ニ立寄リ、 "
                }
            },
            {
                "date": "",
                "text": {
                    "headline": "18:00:00",
                    "text": "<time when=\"18:00:00\"> 午後六時 </time>\n<placename corresp=\"#place_王子\"> 王子 </placename> ニ帰宿ス、後、接骨医師来リ身体ノ痛所ヲ治療ス、夕方及夜ニ入リテ庭園ヲ散歩ス "
                }
            }
        ],
        "zoomify": false,
        "map_type": "osm:standard",
        "map_subdomains": "",
        "attribution": "",
        "language": "jp"
    },
    "font_css": "stock:opensans-gentiumbook"
}