{
    "storymap": {
        "call_to_action": true,
        "call_to_action_text": "",
        "map_as_image": false,
        "slides": [
            {
                "date": "",
                "text": {
                    "headline": "1913-02-11",
                    "text": ""
                },
                "location": {
                    "line": true
                },
                "type": "overview"
            },
            {
                "date": "",
                "text": {
                    "headline": "",
                    "text": "\n"
                }
            },
            {
                "date": "",
                "text": {
                    "headline": "08:00:00",
                    "text": "<time when=\"08:00:00\"> 午前八時 </time> 起床、入浴シテ朝飧ヲ食ス、 <persname corresp=\"#pers_渡辺盛衛\">\n<surname> 渡辺 </surname>\n<forename> 盛衛 </forename>\n</persname> 氏来リ工業学校教員発明ノ事ニ付談話ス、 <placename corresp=\"#place_井頭\"> 井頭 </placename> 感化部幹事\n        <persname corresp=\"#pers_桜井円次郎\">\n<surname> 桜井 </surname>\n<forename> 円次郎 </forename>\n</persname> 氏来話ス、 "
                }
            },
            {
                "date": "",
                "text": {
                    "headline": "11:30:00",
                    "text": "<time when=\"11:30:00\"> 午前十一時半 </time> 内務省衛生局ニ抵リ <placename corresp=\"#place_日本\"> 日本 </placename> 結核病予防協会ノ発会ニ出席ス、一場ノ挨拶ヲ為ス、畢テ <orgname> 埼玉学生誘掖会 </orgname>\n       ニ抵リ午飧シ、後、学友会大会ヲ開キ教育勅語ヲ奉読シ、学生ニ賞品ヲ授与シ、畢テ一場ノ訓示演説ヲ為ス <persname corresp=\"#pers_井上哲次郎\">\n<surname> 井上 </surname>\n<forename> 哲次郎 </forename>\n</persname> 氏、 <persname corresp=\"#pers_本多日照\">\n<surname> 本多 </surname>\n<forename> 日照 </forename>\n</persname> 二氏ノ演説アリ、 "
                }
            },
            {
                "date": "",
                "text": {
                    "headline": "17:00:00",
                    "text": "<time when=\"17:00:00\"> 午後五時 </time> 華族会館ニ抵リ、 <persname corresp=\"#pers_浜尾\">\n<surname> 浜尾 </surname>\n</persname> 、 <persname corresp=\"#pers_菊地\">\n<surname> 菊地 </surname>\n</persname> ノ諸氏ト先儒ノ墳墓保存ノ事ニ付来会者ト協議ス、畢テ夜飧ス、 "
                }
            },
            {
                "date": "",
                "text": {
                    "headline": "20:00:00",
                    "text": "<time when=\"20:00:00\"> 午後八時 </time> 帝国劇場ニ抵リ米人\n        <persname corresp=\"#pers_メヒー\">\n<surname> メヒー </surname>\n</persname> 氏観劇《（ヲ脱カ）》ニ誘引ス、 <persname corresp=\"#pers_新渡戸\">\n<surname> 新渡戸 </surname>\n</persname> 、 <persname corresp=\"#pers_宮岡\">\n<surname> 宮岡 </surname>\n</persname> 二氏夫妻、 <persname corresp=\"#pers_小野\">\n<surname> 小野 </surname>\n</persname> 氏来会ス、夜 "
                }
            },
            {
                "date": "",
                "text": {
                    "headline": "23:00:00",
                    "text": "<time when=\"23:00:00\"> 十一時 </time> 帰宿ス、後、新聞紙ヲ一覧ス "
                }
            }
        ],
        "zoomify": false,
        "map_type": "osm:standard",
        "map_subdomains": "",
        "attribution": "",
        "language": "jp"
    },
    "font_css": "stock:opensans-gentiumbook"
}